pyautoschema/__init__.py
pyautoschema/cli_core.py
pyautoschema/core.py
pyautoschema-0.2.0.dist-info/licenses/LICENSE
pyautoschema-0.2.0.dist-info/METADATA
pyautoschema-0.2.0.dist-info/WHEEL
pyautoschema-0.2.0.dist-info/top_level.txt
pyautoschema-0.2.0.dist-info/RECORD
