Metadata-Version: 2.4
Name: pyautoschema
Version: 0.2.0
Summary: Automatically generate Pydantic models from dictionaries
Author: Shakhobiddin Bozorov
Author-email: Shakhobiddin Bozorov <bozorovshahob27@gmail.com>
License: Shakhobiddin Bozorov
Project-URL: Homepage, https://pypi.org/project/pyautoschema/
Project-URL: Repository, https://github.com/Robben1972/pyautoschema
Requires-Python: >=3.7
License-File: LICENSE
Dynamic: author
Dynamic: license-file
Dynamic: requires-python
